datatables/__init__.py
ninchanese_datatables-0.5.1.dist-info/WHEEL
ninchanese_datatables-0.5.1.dist-info/RECORD
ninchanese_datatables-0.5.1.dist-info/metadata.json
ninchanese_datatables-0.5.1.dist-info/pbr.json
ninchanese_datatables-0.5.1.dist-info/DESCRIPTION.rst
ninchanese_datatables-0.5.1.dist-info/top_level.txt
ninchanese_datatables-0.5.1.dist-info/METADATA
