Metadata-Version: 2.0
Name: ninchanese-datatables
Version: 0.5.1
Summary: Integrates SQLAlchemy with DataTables (framework agnostic) - Containing fixes for ninchanese.com
Home-page: https://github.com/orf/datatables/
Author: Tom
Author-email: tom@tomforb.es
License: MIT
Keywords: sqlalchemy datatables jquery pyramid flask
Platform: UNKNOWN
Classifier: Environment :: Web Environment
Classifier: Framework :: Pyramid
Classifier: Framework :: Flask
Classifier: Framework :: Django
Classifier: Intended Audience :: Developers
Classifier: License :: OSI Approved :: MIT License
Classifier: Programming Language :: Python
Classifier: Programming Language :: Python :: 2
Classifier: Programming Language :: Python :: 2.7
Classifier: Programming Language :: Python :: 3
Classifier: Programming Language :: Python :: 3.2
Classifier: Programming Language :: Python :: 3.3
Classifier: Topic :: Internet :: WWW/HTTP
Classifier: Topic :: Software Development :: Libraries
Classifier: Topic :: Software Development :: Libraries :: Python Modules
